quackdns/__init__.py
quackdns/cli.py
quackdns/config.py
quackdns/core_test.py
quackdns/daemon.py
quackdns/gui.py
quackdns/launcher.py
quackdns/updater.py
quackdns-0.3.1.data/scripts/quackdns-config
quackdns-0.3.1.data/scripts/quackdns-launcher
quackdns-0.3.1.dist-info/DESCRIPTION.rst
quackdns-0.3.1.dist-info/METADATA
quackdns-0.3.1.dist-info/RECORD
quackdns-0.3.1.dist-info/WHEEL
quackdns-0.3.1.dist-info/metadata.json
quackdns-0.3.1.dist-info/top_level.txt
